formprof.py
formtools_formprof-0.1.0.dist-info/licenses/LICENSE
formtools_formprof-0.1.0.dist-info/METADATA
formtools_formprof-0.1.0.dist-info/WHEEL
formtools_formprof-0.1.0.dist-info/entry_points.txt
formtools_formprof-0.1.0.dist-info/top_level.txt
formtools_formprof-0.1.0.dist-info/RECORD
